[
  {
    "OverLapExe": true,
    "ID": 1,
    "ValueLong1": 2100000008,
    "ValueFloat1": 10.0,
    "ValueInt1": 0,
    "ExecutionType": "AddBuffRange",
    "ValueString1": ""
  },
  {
    "OverLapExe": true,
    "ID": 2,
    "ValueLong1": 0,
    "ValueFloat1": 0.0,
    "ValueInt1": 1,
    "ExecutionType": "SendAIMessage",
    "ValueString1": "AlterDestroy"
  },
  {
    "OverLapExe": true,
    "ID": 3,
    "ValueLong1": 0,
    "ValueFloat1": 0.0,
    "ValueInt1": 0,
    "ExecutionType": "SendEventTrigger",
    "ValueString1": ""
  },
  {
    "OverLapExe": true,
    "ID": 4,
    "ValueLong1": 0,
    "ValueFloat1": 0.0,
    "ValueInt1": 0,
    "ExecutionType": "IconBtnEvent",
    "ValueString1": "Interaction_Unknown_Icon"
  },
  {
    "OverLapExe": true,
    "ID": 5,
    "ValueLong1": 103010001,
    "ValueFloat1": 999.0,
    "ValueInt1": 0,
    "ExecutionType": "RemoveBuffRange",
    "ValueString1": ""
  },
  {
    "OverLapExe": true,
    "ID": 6,
    "ValueLong1": 0,
    "ValueFloat1": 0.0,
    "ValueInt1": 0,
    "ExecutionType": "NpcMenu",
    "ValueString1": ""
  },
  {
    "OverLapExe": true,
    "ID": 7,
    "ValueLong1": 0,
    "ValueFloat1": 0.0,
    "ValueInt1": 0,
    "ExecutionType": "PlayProductionTimeLine",
    "ValueString1": "LobbySpawn"
  },
  {
    "OverLapExe": true,
    "ID": 8,
    "ValueLong1": 0,
    "ValueFloat1": 5000.0,
    "ValueInt1": 0,
    "ExecutionType": "NpcSpeech",
    "ValueString1": ""
  },
  {
    "OverLapExe": true,
    "ID": 9,
    "ValueLong1": 0,
    "ValueFloat1": 0.0,
    "ValueInt1": 0,
    "ExecutionType": "TableSpawn",
    "ValueString1": "RedGate_SnowField_Mountain_TriggerScene_WAVE_11"
  },
  {
    "OverLapExe": true,
    "ID": 10,
    "ValueLong1": 360501001,
    "ValueFloat1": 20.0,
    "ValueInt1": 0,
    "ExecutionType": "RemoveBuffRange",
    "ValueString1": ""
  },
  {
    "OverLapExe": true,
    "ID": 11,
    "ValueLong1": 360501011,
    "ValueFloat1": 20.0,
    "ValueInt1": 0,
    "ExecutionType": "RemoveBuffRange",
    "ValueString1": ""
  },
  {
    "OverLapExe": true,
    "ID": 12,
    "ValueLong1": 0,
    "ValueFloat1": 15000.0,
    "ValueInt1": 0,
    "ExecutionType": "NpcSpeech",
    "ValueString1": ""
  },
  {
    "OverLapExe": true,
    "ID": 13,
    "ValueLong1": 0,
    "ValueFloat1": 12000.0,
    "ValueInt1": 0,
    "ExecutionType": "NpcSpeech",
    "ValueString1": ""
  },
  {
    "OverLapExe": true,
    "ID": 14,
    "ValueLong1": 0,
    "ValueFloat1": 0.0,
    "ValueInt1": 64,
    "ExecutionType": "PlayProductionTimeLine",
    "ValueString1": "SocialMotion"
  },
  {
    "OverLapExe": true,
    "ID": 15,
    "ValueLong1": 0,
    "ValueFloat1": 0.0,
    "ValueInt1": 16,
    "ExecutionType": "PlayProductionTimeLine",
    "ValueString1": "SocialMotion"
  },
  {
    "OverLapExe": true,
    "ID": 16,
    "ValueLong1": 0,
    "ValueFloat1": 0.0,
    "ValueInt1": 0,
    "ExecutionType": "TableSpawn",
    "ValueString1": "RedGate_SnowField_Mountain_TriggerScene_WAVE_13"
  },
  {
    "OverLapExe": true,
    "ID": 17,
    "ValueLong1": 0,
    "ValueFloat1": 0.0,
    "ValueInt1": 0,
    "ExecutionType": "TableSpawn",
    "ValueString1": "RedGate_SnowField_Mountain_TriggerScene_WAVE_15"
  },
  {
    "OverLapExe": true,
    "ID": 18,
    "ValueLong1": 0,
    "ValueFloat1": 1.0,
    "ValueInt1": 0,
    "ExecutionType": "ProductionIconBtnEvent",
    "ValueString1": "Btn_Sahdow_Casaca,,400,-50,true,true"
  },
  {
    "OverLapExe": true,
    "ID": 19,
    "ValueLong1": 0,
    "ValueFloat1": 1.0,
    "ValueInt1": 0,
    "ExecutionType": "ProductionIconBtnEvent",
    "ValueString1": "Btn_Sahdow_Igri,,400,-50,true,true"
  },
  {
    "OverLapExe": true,
    "ID": 20,
    "ValueLong1": 0,
    "ValueFloat1": 0.0,
    "ValueInt1": 0,
    "ExecutionType": "ProductionIconBtnEvent",
    "ValueString1": "Btn_Sahdow_Igri,,300,160,False,true"
  },
  {
    "OverLapExe": true,
    "ID": 21,
    "ValueLong1": 0,
    "ValueFloat1": 0.0,
    "ValueInt1": 1,
    "ExecutionType": "SendAIMessage",
    "ValueString1": "IceBear_Bead_A_Dead"
  },
  {
    "OverLapExe": true,
    "ID": 22,
    "ValueLong1": 0,
    "ValueFloat1": 0.0,
    "ValueInt1": 1,
    "ExecutionType": "SendAIMessage",
    "ValueString1": "IceBear_Bead_B_Dead"
  },
  {
    "OverLapExe": true,
    "ID": 23,
    "ValueLong1": 0,
    "ValueFloat1": 0.0,
    "ValueInt1": 1,
    "ExecutionType": "SendAIMessage",
    "ValueString1": "IceBear_Bead_C_Dead"
  },
  {
    "OverLapExe": true,
    "ID": 24,
    "ValueLong1": 0,
    "ValueFloat1": 0.0,
    "ValueInt1": 0,
    "ExecutionType": "ProductionIconBtnEvent",
    "ValueString1": "Btn_Finish_Mob,,400,-50,true,true"
  },
  {
    "OverLapExe": true,
    "ID": 25,
    "ValueLong1": 0,
    "ValueFloat1": 0.0,
    "ValueInt1": 0,
    "ExecutionType": "ProductionIconBtnEvent",
    "ValueString1": ",SysConstStr.GameOption.Control_Device_Touch,400,-50,true,true"
  },
  {
    "OverLapExe": true,
    "ID": 26,
    "ValueLong1": 360501002,
    "ValueFloat1": 20.0,
    "ValueInt1": 0,
    "ExecutionType": "RemoveBuffRange",
    "ValueString1": ""
  },
  {
    "OverLapExe": true,
    "ID": 27,
    "ValueLong1": 360501012,
    "ValueFloat1": 20.0,
    "ValueInt1": 0,
    "ExecutionType": "RemoveBuffRange",
    "ValueString1": ""
  },
  {
    "OverLapExe": true,
    "ID": 28,
    "ValueLong1": 0,
    "ValueFloat1": 7000.0,
    "ValueInt1": 0,
    "ExecutionType": "NpcSpeech",
    "ValueString1": ""
  },
  {
    "OverLapExe": true,
    "ID": 29,
    "ValueLong1": 0,
    "ValueFloat1": 0.0,
    "ValueInt1": 1,
    "ExecutionType": "SendAIMessage",
    "ValueString1": "GolemLabanStoner_Boss_Dead"
  },
  {
    "OverLapExe": true,
    "ID": 30,
    "ValueLong1": 0,
    "ValueFloat1": 0.0,
    "ValueInt1": 0,
    "ExecutionType": "DimensionGate",
    "ValueString1": ""
  }
]