[
  {
    "ID": 1001,
    "SubGroupID": 1001001,
    "RewardType": "Hunter",
    "RewardID": 21,
    "RewardCount": 1
  },
  {
    "ID": 1002,
    "SubGroupID": 1001001,
    "RewardType": "Hunter",
    "RewardID": 31,
    "RewardCount": 1
  },
  {
    "ID": 1003,
    "SubGroupID": 1001001,
    "RewardType": "Hunter",
    "RewardID": 41,
    "RewardCount": 1
  },
  {
    "ID": 1004,
    "SubGroupID": 1001001,
    "RewardType": "Hunter",
    "RewardID": 51,
    "RewardCount": 1
  },
  {
    "ID": 1005,
    "SubGroupID": 1001001,
    "RewardType": "Hunter",
    "RewardID": 81,
    "RewardCount": 1
  },
  {
    "ID": 1006,
    "SubGroupID": 1001001,
    "RewardType": "Hunter",
    "RewardID": 91,
    "RewardCount": 1
  },
  {
    "ID": 1007,
    "SubGroupID": 1001001,
    "RewardType": "Hunter",
    "RewardID": 101,
    "RewardCount": 1
  },
  {
    "ID": 1008,
    "SubGroupID": 1001001,
    "RewardType": "Hunter",
    "RewardID": 111,
    "RewardCount": 1
  },
  {
    "ID": 1009,
    "SubGroupID": 1001001,
    "RewardType": "Hunter",
    "RewardID": 121,
    "RewardCount": 1
  },
  {
    "ID": 1010,
    "SubGroupID": 1001001,
    "RewardType": "Hunter",
    "RewardID": 141,
    "RewardCount": 1
  },
  {
    "ID": 1011,
    "SubGroupID": 1001001,
    "RewardType": "Hunter",
    "RewardID": 211,
    "RewardCount": 1
  },
  {
    "ID": 1012,
    "SubGroupID": 1001001,
    "RewardType": "Hunter",
    "RewardID": 221,
    "RewardCount": 1
  },
  {
    "ID": 1013,
    "SubGroupID": 1001001,
    "RewardType": "Hunter",
    "RewardID": 231,
    "RewardCount": 1
  },
  {
    "ID": 2001,
    "SubGroupID": 1002001,
    "RewardType": "Hunter",
    "RewardID": 62,
    "RewardCount": 1
  },
  {
    "ID": 2002,
    "SubGroupID": 1002001,
    "RewardType": "Hunter",
    "RewardID": 71,
    "RewardCount": 1
  },
  {
    "ID": 2003,
    "SubGroupID": 1002001,
    "RewardType": "Hunter",
    "RewardID": 151,
    "RewardCount": 1
  },
  {
    "ID": 2004,
    "SubGroupID": 1002001,
    "RewardType": "Hunter",
    "RewardID": 161,
    "RewardCount": 1
  },
  {
    "ID": 2005,
    "SubGroupID": 1002001,
    "RewardType": "Hunter",
    "RewardID": 171,
    "RewardCount": 1
  },
  {
    "ID": 2006,
    "SubGroupID": 1002001,
    "RewardType": "Hunter",
    "RewardID": 181,
    "RewardCount": 1
  },
  {
    "ID": 2007,
    "SubGroupID": 1002001,
    "RewardType": "Hunter",
    "RewardID": 201,
    "RewardCount": 1
  },
  {
    "ID": 2008,
    "SubGroupID": 1002001,
    "RewardType": "Hunter",
    "RewardID": 251,
    "RewardCount": 1
  },
  {
    "ID": 3001,
    "SubGroupID": 1011001,
    "RewardType": "Relic",
    "RewardID": 302020001,
    "RewardCount": 1
  },
  {
    "ID": 3002,
    "SubGroupID": 1011001,
    "RewardType": "Relic",
    "RewardID": 302020002,
    "RewardCount": 1
  },
  {
    "ID": 3003,
    "SubGroupID": 1011001,
    "RewardType": "Relic",
    "RewardID": 302020003,
    "RewardCount": 1
  },
  {
    "ID": 3004,
    "SubGroupID": 1011001,
    "RewardType": "Relic",
    "RewardID": 302020004,
    "RewardCount": 1
  },
  {
    "ID": 3005,
    "SubGroupID": 1011001,
    "RewardType": "Relic",
    "RewardID": 302020005,
    "RewardCount": 1
  },
  {
    "ID": 3006,
    "SubGroupID": 1011001,
    "RewardType": "Relic",
    "RewardID": 302020006,
    "RewardCount": 1
  },
  {
    "ID": 3007,
    "SubGroupID": 1011001,
    "RewardType": "Relic",
    "RewardID": 302020007,
    "RewardCount": 1
  },
  {
    "ID": 3008,
    "SubGroupID": 1011001,
    "RewardType": "Relic",
    "RewardID": 302020008,
    "RewardCount": 1
  },
  {
    "ID": 3009,
    "SubGroupID": 1011001,
    "RewardType": "Relic",
    "RewardID": 302020009,
    "RewardCount": 1
  },
  {
    "ID": 3010,
    "SubGroupID": 1011001,
    "RewardType": "Relic",
    "RewardID": 302020010,
    "RewardCount": 1
  },
  {
    "ID": 3012,
    "SubGroupID": 1011001,
    "RewardType": "Relic",
    "RewardID": 302030002,
    "RewardCount": 1
  },
  {
    "ID": 3013,
    "SubGroupID": 1011001,
    "RewardType": "Relic",
    "RewardID": 302030003,
    "RewardCount": 1
  },
  {
    "ID": 3015,
    "SubGroupID": 1011001,
    "RewardType": "Relic",
    "RewardID": 302030005,
    "RewardCount": 1
  },
  {
    "ID": 3016,
    "SubGroupID": 1011001,
    "RewardType": "Relic",
    "RewardID": 302030006,
    "RewardCount": 1
  },
  {
    "ID": 3017,
    "SubGroupID": 1011001,
    "RewardType": "Relic",
    "RewardID": 302030007,
    "RewardCount": 1
  },
  {
    "ID": 3018,
    "SubGroupID": 1011001,
    "RewardType": "Relic",
    "RewardID": 302030008,
    "RewardCount": 1
  },
  {
    "ID": 3020,
    "SubGroupID": 1011001,
    "RewardType": "Relic",
    "RewardID": 302030010,
    "RewardCount": 1
  },
  {
    "ID": 3021,
    "SubGroupID": 1011001,
    "RewardType": "Relic",
    "RewardID": 302030011,
    "RewardCount": 1
  },
  {
    "ID": 3022,
    "SubGroupID": 1011001,
    "RewardType": "Relic",
    "RewardID": 302030012,
    "RewardCount": 1
  },
  {
    "ID": 3023,
    "SubGroupID": 1011001,
    "RewardType": "Relic",
    "RewardID": 302030013,
    "RewardCount": 1
  },
  {
    "ID": 3024,
    "SubGroupID": 1011001,
    "RewardType": "Relic",
    "RewardID": 302030014,
    "RewardCount": 1
  },
  {
    "ID": 3025,
    "SubGroupID": 1011001,
    "RewardType": "Relic",
    "RewardID": 302030015,
    "RewardCount": 1
  },
  {
    "ID": 4001,
    "SubGroupID": 1021001,
    "RewardType": "GS",
    "RewardID": 200030001,
    "RewardCount": 1
  },
  {
    "ID": 4002,
    "SubGroupID": 1021001,
    "RewardType": "GS",
    "RewardID": 200030002,
    "RewardCount": 1
  },
  {
    "ID": 4003,
    "SubGroupID": 1021001,
    "RewardType": "GS",
    "RewardID": 200030003,
    "RewardCount": 1
  },
  {
    "ID": 4004,
    "SubGroupID": 1021001,
    "RewardType": "GS",
    "RewardID": 200030004,
    "RewardCount": 1
  },
  {
    "ID": 4005,
    "SubGroupID": 1021001,
    "RewardType": "GS",
    "RewardID": 200030005,
    "RewardCount": 1
  },
  {
    "ID": 4006,
    "SubGroupID": 1021001,
    "RewardType": "GS",
    "RewardID": 200020005,
    "RewardCount": 1
  },
  {
    "ID": 4007,
    "SubGroupID": 1021001,
    "RewardType": "GS",
    "RewardID": 200020001,
    "RewardCount": 1
  },
  {
    "ID": 4008,
    "SubGroupID": 1021001,
    "RewardType": "GS",
    "RewardID": 200020002,
    "RewardCount": 1
  },
  {
    "ID": 4009,
    "SubGroupID": 1021001,
    "RewardType": "GS",
    "RewardID": 200020003,
    "RewardCount": 1
  },
  {
    "ID": 4010,
    "SubGroupID": 1021001,
    "RewardType": "GS",
    "RewardID": 200020004,
    "RewardCount": 1
  },
  {
    "ID": 4011,
    "SubGroupID": 1021001,
    "RewardType": "GS",
    "RewardID": 200020007,
    "RewardCount": 1
  },
  {
    "ID": 4012,
    "SubGroupID": 1021001,
    "RewardType": "GS",
    "RewardID": 200020010,
    "RewardCount": 1
  },
  {
    "ID": 4013,
    "SubGroupID": 1021001,
    "RewardType": "GS",
    "RewardID": 200020006,
    "RewardCount": 1
  },
  {
    "ID": 4014,
    "SubGroupID": 1021001,
    "RewardType": "GS",
    "RewardID": 200020011,
    "RewardCount": 1
  },
  {
    "ID": 4015,
    "SubGroupID": 1021001,
    "RewardType": "GS",
    "RewardID": 200020008,
    "RewardCount": 1
  },
  {
    "ID": 4016,
    "SubGroupID": 1021001,
    "RewardType": "GS",
    "RewardID": 200020009,
    "RewardCount": 1
  },
  {
    "ID": 4017,
    "SubGroupID": 1021001,
    "RewardType": "GS",
    "RewardID": 200010008,
    "RewardCount": 1
  },
  {
    "ID": 4018,
    "SubGroupID": 1021001,
    "RewardType": "GS",
    "RewardID": 200010007,
    "RewardCount": 1
  },
  {
    "ID": 4019,
    "SubGroupID": 1021001,
    "RewardType": "GS",
    "RewardID": 200010011,
    "RewardCount": 1
  },
  {
    "ID": 4020,
    "SubGroupID": 1021001,
    "RewardType": "GS",
    "RewardID": 200010009,
    "RewardCount": 1
  },
  {
    "ID": 4021,
    "SubGroupID": 1021001,
    "RewardType": "GS",
    "RewardID": 200010012,
    "RewardCount": 1
  },
  {
    "ID": 4022,
    "SubGroupID": 1021001,
    "RewardType": "GS",
    "RewardID": 200010004,
    "RewardCount": 1
  },
  {
    "ID": 4023,
    "SubGroupID": 1021001,
    "RewardType": "GS",
    "RewardID": 200010013,
    "RewardCount": 1
  },
  {
    "ID": 4024,
    "SubGroupID": 1021001,
    "RewardType": "GS",
    "RewardID": 200010014,
    "RewardCount": 1
  },
  {
    "ID": 4025,
    "SubGroupID": 1021001,
    "RewardType": "GS",
    "RewardID": 200010010,
    "RewardCount": 1
  },
  {
    "ID": 8001,
    "SubGroupID": 1061001,
    "RewardType": "Gold",
    "RewardID": 1000003,
    "RewardCount": 3000
  },
  {
    "ID": 8002,
    "SubGroupID": 1061001,
    "RewardType": "Material",
    "RewardID": 10050001,
    "RewardCount": 15
  },
  {
    "ID": 8003,
    "SubGroupID": 1061001,
    "RewardType": "Material",
    "RewardID": 10160001,
    "RewardCount": 10
  },
  {
    "ID": 9001,
    "SubGroupID": 1071001,
    "RewardType": "Hunter",
    "RewardID": 71,
    "RewardCount": 1
  },
  {
    "ID": 9002,
    "SubGroupID": 1071001,
    "RewardType": "Hunter",
    "RewardID": 151,
    "RewardCount": 1
  },
  {
    "ID": 9003,
    "SubGroupID": 1071001,
    "RewardType": "Hunter",
    "RewardID": 201,
    "RewardCount": 1
  },
  {
    "ID": 9004,
    "SubGroupID": 1071001,
    "RewardType": "Hunter",
    "RewardID": 171,
    "RewardCount": 1
  },
  {
    "ID": 9005,
    "SubGroupID": 1071001,
    "RewardType": "Hunter",
    "RewardID": 161,
    "RewardCount": 1
  },
  {
    "ID": 9006,
    "SubGroupID": 1071001,
    "RewardType": "Hunter",
    "RewardID": 181,
    "RewardCount": 1
  },
  {
    "ID": 9007,
    "SubGroupID": 1071001,
    "RewardType": "Hunter",
    "RewardID": 62,
    "RewardCount": 1
  },
  {
    "ID": 9008,
    "SubGroupID": 1071001,
    "RewardType": "Hunter",
    "RewardID": 251,
    "RewardCount": 1
  },
  {
    "ID": 9009,
    "SubGroupID": 1071001,
    "RewardType": "Hunter",
    "RewardID": 131,
    "RewardCount": 1
  },
  {
    "ID": 9010,
    "SubGroupID": 1071001,
    "RewardType": "Hunter",
    "RewardID": 61,
    "RewardCount": 1
  },
  {
    "ID": 9101,
    "SubGroupID": 1071002,
    "RewardType": "GS",
    "RewardID": 200030001,
    "RewardCount": 1
  },
  {
    "ID": 9102,
    "SubGroupID": 1071002,
    "RewardType": "GS",
    "RewardID": 200030002,
    "RewardCount": 1
  },
  {
    "ID": 9103,
    "SubGroupID": 1071002,
    "RewardType": "GS",
    "RewardID": 200030003,
    "RewardCount": 1
  },
  {
    "ID": 9104,
    "SubGroupID": 1071002,
    "RewardType": "GS",
    "RewardID": 200030004,
    "RewardCount": 1
  },
  {
    "ID": 9105,
    "SubGroupID": 1071002,
    "RewardType": "GS",
    "RewardID": 200030005,
    "RewardCount": 1
  },
  {
    "ID": 9106,
    "SubGroupID": 1071002,
    "RewardType": "GS",
    "RewardID": 200020005,
    "RewardCount": 1
  },
  {
    "ID": 9201,
    "SubGroupID": 1071003,
    "RewardType": "Relic",
    "RewardID": 302020001,
    "RewardCount": 1
  },
  {
    "ID": 9202,
    "SubGroupID": 1071003,
    "RewardType": "Relic",
    "RewardID": 302020002,
    "RewardCount": 1
  },
  {
    "ID": 9203,
    "SubGroupID": 1071003,
    "RewardType": "Relic",
    "RewardID": 302020003,
    "RewardCount": 1
  },
  {
    "ID": 9204,
    "SubGroupID": 1071003,
    "RewardType": "Relic",
    "RewardID": 302020004,
    "RewardCount": 1
  },
  {
    "ID": 9205,
    "SubGroupID": 1071003,
    "RewardType": "Relic",
    "RewardID": 302020005,
    "RewardCount": 1
  },
  {
    "ID": 9206,
    "SubGroupID": 1071003,
    "RewardType": "Relic",
    "RewardID": 302020006,
    "RewardCount": 1
  },
  {
    "ID": 9207,
    "SubGroupID": 1071003,
    "RewardType": "Relic",
    "RewardID": 302020007,
    "RewardCount": 1
  },
  {
    "ID": 9208,
    "SubGroupID": 1071003,
    "RewardType": "Relic",
    "RewardID": 302020008,
    "RewardCount": 1
  },
  {
    "ID": 9209,
    "SubGroupID": 1071003,
    "RewardType": "Relic",
    "RewardID": 302020009,
    "RewardCount": 1
  },
  {
    "ID": 9210,
    "SubGroupID": 1071003,
    "RewardType": "Relic",
    "RewardID": 302020010,
    "RewardCount": 1
  },
  {
    "ID": 9211,
    "SubGroupID": 1071003,
    "RewardType": "Relic",
    "RewardID": 302030001,
    "RewardCount": 1
  },
  {
    "ID": 9212,
    "SubGroupID": 1071003,
    "RewardType": "Relic",
    "RewardID": 302030002,
    "RewardCount": 1
  },
  {
    "ID": 9213,
    "SubGroupID": 1071003,
    "RewardType": "Relic",
    "RewardID": 302030003,
    "RewardCount": 1
  },
  {
    "ID": 9214,
    "SubGroupID": 1071003,
    "RewardType": "Relic",
    "RewardID": 302030005,
    "RewardCount": 1
  },
  {
    "ID": 9215,
    "SubGroupID": 1071003,
    "RewardType": "Relic",
    "RewardID": 302030006,
    "RewardCount": 1
  },
  {
    "ID": 9216,
    "SubGroupID": 1071003,
    "RewardType": "Relic",
    "RewardID": 302030007,
    "RewardCount": 1
  },
  {
    "ID": 9217,
    "SubGroupID": 1071003,
    "RewardType": "Relic",
    "RewardID": 302030008,
    "RewardCount": 1
  },
  {
    "ID": 9218,
    "SubGroupID": 1071003,
    "RewardType": "Relic",
    "RewardID": 302030010,
    "RewardCount": 1
  },
  {
    "ID": 9219,
    "SubGroupID": 1071003,
    "RewardType": "Relic",
    "RewardID": 302030011,
    "RewardCount": 1
  },
  {
    "ID": 9220,
    "SubGroupID": 1071003,
    "RewardType": "Relic",
    "RewardID": 302030012,
    "RewardCount": 1
  },
  {
    "ID": 9221,
    "SubGroupID": 1071003,
    "RewardType": "Relic",
    "RewardID": 302030013,
    "RewardCount": 1
  },
  {
    "ID": 9222,
    "SubGroupID": 1071003,
    "RewardType": "Relic",
    "RewardID": 302030014,
    "RewardCount": 1
  },
  {
    "ID": 9223,
    "SubGroupID": 1071003,
    "RewardType": "Relic",
    "RewardID": 302030015,
    "RewardCount": 1
  },
  {
    "ID": 10001,
    "SubGroupID": 1081001,
    "RewardType": "Material",
    "RewardID": 10041001,
    "RewardCount": 1
  },
  {
    "ID": 10002,
    "SubGroupID": 1081001,
    "RewardType": "Material",
    "RewardID": 10041002,
    "RewardCount": 1
  },
  {
    "ID": 10003,
    "SubGroupID": 1081001,
    "RewardType": "Material",
    "RewardID": 10041003,
    "RewardCount": 1
  },
  {
    "ID": 10004,
    "SubGroupID": 1081001,
    "RewardType": "Material",
    "RewardID": 10041004,
    "RewardCount": 1
  },
  {
    "ID": 10005,
    "SubGroupID": 1081001,
    "RewardType": "Material",
    "RewardID": 10041005,
    "RewardCount": 1
  },
  {
    "ID": 10006,
    "SubGroupID": 1091001,
    "RewardType": "Material",
    "RewardID": 10160006,
    "RewardCount": 1
  },
  {
    "ID": 10007,
    "SubGroupID": 1091001,
    "RewardType": "Material",
    "RewardID": 10160007,
    "RewardCount": 1
  },
  {
    "ID": 10008,
    "SubGroupID": 1091001,
    "RewardType": "Material",
    "RewardID": 10160008,
    "RewardCount": 1
  },
  {
    "ID": 10009,
    "SubGroupID": 1091001,
    "RewardType": "Material",
    "RewardID": 10160009,
    "RewardCount": 1
  },
  {
    "ID": 10010,
    "SubGroupID": 1091001,
    "RewardType": "Material",
    "RewardID": 10160010,
    "RewardCount": 1
  },
  {
    "ID": 10011,
    "SubGroupID": 1091002,
    "RewardType": "Material",
    "RewardID": 10031007,
    "RewardCount": 30
  },
  {
    "ID": 10012,
    "SubGroupID": 1091002,
    "RewardType": "Material",
    "RewardID": 10031008,
    "RewardCount": 10
  },
  {
    "ID": 10013,
    "SubGroupID": 1091002,
    "RewardType": "Material",
    "RewardID": 10031009,
    "RewardCount": 3
  },
  {
    "ID": 10014,
    "SubGroupID": 1091002,
    "RewardType": "Material",
    "RewardID": 10021001,
    "RewardCount": 2
  },
  {
    "ID": 10015,
    "SubGroupID": 1091003,
    "RewardType": "Material",
    "RewardID": 10020001,
    "RewardCount": 150
  },
  {
    "ID": 10016,
    "SubGroupID": 1091003,
    "RewardType": "Material",
    "RewardID": 10020002,
    "RewardCount": 50
  },
  {
    "ID": 10017,
    "SubGroupID": 1091003,
    "RewardType": "Material",
    "RewardID": 10020003,
    "RewardCount": 15
  },
  {
    "ID": 10030,
    "SubGroupID": 1091004,
    "RewardType": "Artifact",
    "RewardID": 450210131,
    "RewardCount": 1
  },
  {
    "ID": 10031,
    "SubGroupID": 1091004,
    "RewardType": "Artifact",
    "RewardID": 450210132,
    "RewardCount": 1
  },
  {
    "ID": 10032,
    "SubGroupID": 1091004,
    "RewardType": "Artifact",
    "RewardID": 450210133,
    "RewardCount": 1
  },
  {
    "ID": 10033,
    "SubGroupID": 1091004,
    "RewardType": "Artifact",
    "RewardID": 450210134,
    "RewardCount": 1
  },
  {
    "ID": 10034,
    "SubGroupID": 1091004,
    "RewardType": "Artifact",
    "RewardID": 450210135,
    "RewardCount": 1
  },
  {
    "ID": 10035,
    "SubGroupID": 1091004,
    "RewardType": "Artifact",
    "RewardID": 450210136,
    "RewardCount": 1
  },
  {
    "ID": 10036,
    "SubGroupID": 1091004,
    "RewardType": "Artifact",
    "RewardID": 450210137,
    "RewardCount": 1
  },
  {
    "ID": 10037,
    "SubGroupID": 1091004,
    "RewardType": "Artifact",
    "RewardID": 450210138,
    "RewardCount": 1
  },
  {
    "ID": 10038,
    "SubGroupID": 1091005,
    "RewardType": "Artifact",
    "RewardID": 450110131,
    "RewardCount": 1
  },
  {
    "ID": 10039,
    "SubGroupID": 1091005,
    "RewardType": "Artifact",
    "RewardID": 450110132,
    "RewardCount": 1
  },
  {
    "ID": 10040,
    "SubGroupID": 1091005,
    "RewardType": "Artifact",
    "RewardID": 450110133,
    "RewardCount": 1
  },
  {
    "ID": 10041,
    "SubGroupID": 1091005,
    "RewardType": "Artifact",
    "RewardID": 450110134,
    "RewardCount": 1
  },
  {
    "ID": 10042,
    "SubGroupID": 1091005,
    "RewardType": "Artifact",
    "RewardID": 450110135,
    "RewardCount": 1
  },
  {
    "ID": 10043,
    "SubGroupID": 1091005,
    "RewardType": "Artifact",
    "RewardID": 450110136,
    "RewardCount": 1
  },
  {
    "ID": 10044,
    "SubGroupID": 1091005,
    "RewardType": "Artifact",
    "RewardID": 450110137,
    "RewardCount": 1
  },
  {
    "ID": 10045,
    "SubGroupID": 1091005,
    "RewardType": "Artifact",
    "RewardID": 450110138,
    "RewardCount": 1
  },
  {
    "ID": 10046,
    "SubGroupID": 1091006,
    "RewardType": "Artifact",
    "RewardID": 450310131,
    "RewardCount": 1
  },
  {
    "ID": 10047,
    "SubGroupID": 1091006,
    "RewardType": "Artifact",
    "RewardID": 450310132,
    "RewardCount": 1
  },
  {
    "ID": 10048,
    "SubGroupID": 1091006,
    "RewardType": "Artifact",
    "RewardID": 450310133,
    "RewardCount": 1
  },
  {
    "ID": 10049,
    "SubGroupID": 1091006,
    "RewardType": "Artifact",
    "RewardID": 450310134,
    "RewardCount": 1
  },
  {
    "ID": 10050,
    "SubGroupID": 1091006,
    "RewardType": "Artifact",
    "RewardID": 450310135,
    "RewardCount": 1
  },
  {
    "ID": 10051,
    "SubGroupID": 1091006,
    "RewardType": "Artifact",
    "RewardID": 450310136,
    "RewardCount": 1
  },
  {
    "ID": 10052,
    "SubGroupID": 1091006,
    "RewardType": "Artifact",
    "RewardID": 450310137,
    "RewardCount": 1
  },
  {
    "ID": 10053,
    "SubGroupID": 1091006,
    "RewardType": "Artifact",
    "RewardID": 450310138,
    "RewardCount": 1
  },
  {
    "ID": 10054,
    "SubGroupID": 1091007,
    "RewardType": "Artifact",
    "RewardID": 450210141,
    "RewardCount": 1
  },
  {
    "ID": 10055,
    "SubGroupID": 1091007,
    "RewardType": "Artifact",
    "RewardID": 450210142,
    "RewardCount": 1
  },
  {
    "ID": 10056,
    "SubGroupID": 1091007,
    "RewardType": "Artifact",
    "RewardID": 450210143,
    "RewardCount": 1
  },
  {
    "ID": 10057,
    "SubGroupID": 1091007,
    "RewardType": "Artifact",
    "RewardID": 450210144,
    "RewardCount": 1
  },
  {
    "ID": 10058,
    "SubGroupID": 1091007,
    "RewardType": "Artifact",
    "RewardID": 450210145,
    "RewardCount": 1
  },
  {
    "ID": 10059,
    "SubGroupID": 1091007,
    "RewardType": "Artifact",
    "RewardID": 450210146,
    "RewardCount": 1
  },
  {
    "ID": 10060,
    "SubGroupID": 1091007,
    "RewardType": "Artifact",
    "RewardID": 450210147,
    "RewardCount": 1
  },
  {
    "ID": 10061,
    "SubGroupID": 1091007,
    "RewardType": "Artifact",
    "RewardID": 450210148,
    "RewardCount": 1
  },
  {
    "ID": 10062,
    "SubGroupID": 1091008,
    "RewardType": "Artifact",
    "RewardID": 450110141,
    "RewardCount": 1
  },
  {
    "ID": 10063,
    "SubGroupID": 1091008,
    "RewardType": "Artifact",
    "RewardID": 450110142,
    "RewardCount": 1
  },
  {
    "ID": 10064,
    "SubGroupID": 1091008,
    "RewardType": "Artifact",
    "RewardID": 450110143,
    "RewardCount": 1
  },
  {
    "ID": 10065,
    "SubGroupID": 1091008,
    "RewardType": "Artifact",
    "RewardID": 450110144,
    "RewardCount": 1
  },
  {
    "ID": 10066,
    "SubGroupID": 1091008,
    "RewardType": "Artifact",
    "RewardID": 450110145,
    "RewardCount": 1
  },
  {
    "ID": 10067,
    "SubGroupID": 1091008,
    "RewardType": "Artifact",
    "RewardID": 450110146,
    "RewardCount": 1
  },
  {
    "ID": 10068,
    "SubGroupID": 1091008,
    "RewardType": "Artifact",
    "RewardID": 450110147,
    "RewardCount": 1
  },
  {
    "ID": 10069,
    "SubGroupID": 1091008,
    "RewardType": "Artifact",
    "RewardID": 450110148,
    "RewardCount": 1
  },
  {
    "ID": 10070,
    "SubGroupID": 1091009,
    "RewardType": "Artifact",
    "RewardID": 450310141,
    "RewardCount": 1
  },
  {
    "ID": 10071,
    "SubGroupID": 1091009,
    "RewardType": "Artifact",
    "RewardID": 450310142,
    "RewardCount": 1
  },
  {
    "ID": 10072,
    "SubGroupID": 1091009,
    "RewardType": "Artifact",
    "RewardID": 450310143,
    "RewardCount": 1
  },
  {
    "ID": 10073,
    "SubGroupID": 1091009,
    "RewardType": "Artifact",
    "RewardID": 450310144,
    "RewardCount": 1
  },
  {
    "ID": 10074,
    "SubGroupID": 1091009,
    "RewardType": "Artifact",
    "RewardID": 450310145,
    "RewardCount": 1
  },
  {
    "ID": 10075,
    "SubGroupID": 1091009,
    "RewardType": "Artifact",
    "RewardID": 450310146,
    "RewardCount": 1
  },
  {
    "ID": 10076,
    "SubGroupID": 1091009,
    "RewardType": "Artifact",
    "RewardID": 450310147,
    "RewardCount": 1
  },
  {
    "ID": 10077,
    "SubGroupID": 1091009,
    "RewardType": "Artifact",
    "RewardID": 450310148,
    "RewardCount": 1
  },
  {
    "ID": 999001,
    "SubGroupID": 9999,
    "RewardType": "Active",
    "RewardID": 110012001,
    "RewardCount": 1
  },
  {
    "ID": 999002,
    "SubGroupID": 9999,
    "RewardType": "Active",
    "RewardID": 110013001,
    "RewardCount": 1
  },
  {
    "ID": 999003,
    "SubGroupID": 9999,
    "RewardType": "Active",
    "RewardID": 110014001,
    "RewardCount": 1
  },
  {
    "ID": 999004,
    "SubGroupID": 9999,
    "RewardType": "Active",
    "RewardID": 110012002,
    "RewardCount": 1
  },
  {
    "ID": 999005,
    "SubGroupID": 9999,
    "RewardType": "Active",
    "RewardID": 110013002,
    "RewardCount": 1
  },
  {
    "ID": 999006,
    "SubGroupID": 9999,
    "RewardType": "Active",
    "RewardID": 110014002,
    "RewardCount": 1
  },
  {
    "ID": 999007,
    "SubGroupID": 9999,
    "RewardType": "Active",
    "RewardID": 110012003,
    "RewardCount": 1
  },
  {
    "ID": 999008,
    "SubGroupID": 9999,
    "RewardType": "Active",
    "RewardID": 110013003,
    "RewardCount": 1
  },
  {
    "ID": 999009,
    "SubGroupID": 9999,
    "RewardType": "Active",
    "RewardID": 110014003,
    "RewardCount": 1
  },
  {
    "ID": 999010,
    "SubGroupID": 9999,
    "RewardType": "Active",
    "RewardID": 110012004,
    "RewardCount": 1
  },
  {
    "ID": 999011,
    "SubGroupID": 9999,
    "RewardType": "Active",
    "RewardID": 110013004,
    "RewardCount": 1
  },
  {
    "ID": 999012,
    "SubGroupID": 9999,
    "RewardType": "Active",
    "RewardID": 110014004,
    "RewardCount": 1
  },
  {
    "ID": 999013,
    "SubGroupID": 9999,
    "RewardType": "Active",
    "RewardID": 110022001,
    "RewardCount": 1
  },
  {
    "ID": 999014,
    "SubGroupID": 9999,
    "RewardType": "Active",
    "RewardID": 110023001,
    "RewardCount": 1
  },
  {
    "ID": 999015,
    "SubGroupID": 9999,
    "RewardType": "Active",
    "RewardID": 110024001,
    "RewardCount": 1
  },
  {
    "ID": 999016,
    "SubGroupID": 9999,
    "RewardType": "Active",
    "RewardID": 110022002,
    "RewardCount": 1
  },
  {
    "ID": 999017,
    "SubGroupID": 9999,
    "RewardType": "Active",
    "RewardID": 110023002,
    "RewardCount": 1
  },
  {
    "ID": 999018,
    "SubGroupID": 9999,
    "RewardType": "Active",
    "RewardID": 110024002,
    "RewardCount": 1
  },
  {
    "ID": 999019,
    "SubGroupID": 9999,
    "RewardType": "Active",
    "RewardID": 110022003,
    "RewardCount": 1
  },
  {
    "ID": 999020,
    "SubGroupID": 9999,
    "RewardType": "Active",
    "RewardID": 110023003,
    "RewardCount": 1
  },
  {
    "ID": 999021,
    "SubGroupID": 9999,
    "RewardType": "Active",
    "RewardID": 110024003,
    "RewardCount": 1
  },
  {
    "ID": 999022,
    "SubGroupID": 9999,
    "RewardType": "Active",
    "RewardID": 110022004,
    "RewardCount": 1
  },
  {
    "ID": 999023,
    "SubGroupID": 9999,
    "RewardType": "Active",
    "RewardID": 110023004,
    "RewardCount": 1
  },
  {
    "ID": 999024,
    "SubGroupID": 9999,
    "RewardType": "Active",
    "RewardID": 110024004,
    "RewardCount": 1
  },
  {
    "ID": 999025,
    "SubGroupID": 9999,
    "RewardType": "Active",
    "RewardID": 110032001,
    "RewardCount": 1
  },
  {
    "ID": 999026,
    "SubGroupID": 9999,
    "RewardType": "Active",
    "RewardID": 110033001,
    "RewardCount": 1
  },
  {
    "ID": 999027,
    "SubGroupID": 9999,
    "RewardType": "Active",
    "RewardID": 110034001,
    "RewardCount": 1
  },
  {
    "ID": 999028,
    "SubGroupID": 9999,
    "RewardType": "Active",
    "RewardID": 110032002,
    "RewardCount": 1
  },
  {
    "ID": 999029,
    "SubGroupID": 9999,
    "RewardType": "Active",
    "RewardID": 110033002,
    "RewardCount": 1
  },
  {
    "ID": 999030,
    "SubGroupID": 9999,
    "RewardType": "Active",
    "RewardID": 110034002,
    "RewardCount": 1
  },
  {
    "ID": 999031,
    "SubGroupID": 9999,
    "RewardType": "Active",
    "RewardID": 110032003,
    "RewardCount": 1
  },
  {
    "ID": 999032,
    "SubGroupID": 9999,
    "RewardType": "Active",
    "RewardID": 110033003,
    "RewardCount": 1
  },
  {
    "ID": 999033,
    "SubGroupID": 9999,
    "RewardType": "Active",
    "RewardID": 110034003,
    "RewardCount": 1
  },
  {
    "ID": 999034,
    "SubGroupID": 9999,
    "RewardType": "Active",
    "RewardID": 110032004,
    "RewardCount": 1
  },
  {
    "ID": 999035,
    "SubGroupID": 9999,
    "RewardType": "Active",
    "RewardID": 110033004,
    "RewardCount": 1
  },
  {
    "ID": 999036,
    "SubGroupID": 9999,
    "RewardType": "Active",
    "RewardID": 110034004,
    "RewardCount": 1
  },
  {
    "ID": 999037,
    "SubGroupID": 9999,
    "RewardType": "Active",
    "RewardID": 110042001,
    "RewardCount": 1
  },
  {
    "ID": 999038,
    "SubGroupID": 9999,
    "RewardType": "Active",
    "RewardID": 110043001,
    "RewardCount": 1
  },
  {
    "ID": 999039,
    "SubGroupID": 9999,
    "RewardType": "Active",
    "RewardID": 110044001,
    "RewardCount": 1
  },
  {
    "ID": 999040,
    "SubGroupID": 9999,
    "RewardType": "Active",
    "RewardID": 110042002,
    "RewardCount": 1
  },
  {
    "ID": 999041,
    "SubGroupID": 9999,
    "RewardType": "Active",
    "RewardID": 110043002,
    "RewardCount": 1
  },
  {
    "ID": 999042,
    "SubGroupID": 9999,
    "RewardType": "Active",
    "RewardID": 110044002,
    "RewardCount": 1
  },
  {
    "ID": 999043,
    "SubGroupID": 9999,
    "RewardType": "Active",
    "RewardID": 110042003,
    "RewardCount": 1
  },
  {
    "ID": 999044,
    "SubGroupID": 9999,
    "RewardType": "Active",
    "RewardID": 110043003,
    "RewardCount": 1
  },
  {
    "ID": 999045,
    "SubGroupID": 9999,
    "RewardType": "Active",
    "RewardID": 110044003,
    "RewardCount": 1
  },
  {
    "ID": 999046,
    "SubGroupID": 9999,
    "RewardType": "Active",
    "RewardID": 110042004,
    "RewardCount": 1
  },
  {
    "ID": 999047,
    "SubGroupID": 9999,
    "RewardType": "Active",
    "RewardID": 110043004,
    "RewardCount": 1
  },
  {
    "ID": 999048,
    "SubGroupID": 9999,
    "RewardType": "Active",
    "RewardID": 110044004,
    "RewardCount": 1
  },
  {
    "ID": 999049,
    "SubGroupID": 9999,
    "RewardType": "Active",
    "RewardID": 110052001,
    "RewardCount": 1
  },
  {
    "ID": 999050,
    "SubGroupID": 9999,
    "RewardType": "Active",
    "RewardID": 110053001,
    "RewardCount": 1
  },
  {
    "ID": 999051,
    "SubGroupID": 9999,
    "RewardType": "Active",
    "RewardID": 110054001,
    "RewardCount": 1
  },
  {
    "ID": 999052,
    "SubGroupID": 9999,
    "RewardType": "Active",
    "RewardID": 110052002,
    "RewardCount": 1
  },
  {
    "ID": 999053,
    "SubGroupID": 9999,
    "RewardType": "Active",
    "RewardID": 110053002,
    "RewardCount": 1
  },
  {
    "ID": 999054,
    "SubGroupID": 9999,
    "RewardType": "Active",
    "RewardID": 110054002,
    "RewardCount": 1
  },
  {
    "ID": 999055,
    "SubGroupID": 9999,
    "RewardType": "Active",
    "RewardID": 110052003,
    "RewardCount": 1
  },
  {
    "ID": 999056,
    "SubGroupID": 9999,
    "RewardType": "Active",
    "RewardID": 110053003,
    "RewardCount": 1
  },
  {
    "ID": 999057,
    "SubGroupID": 9999,
    "RewardType": "Active",
    "RewardID": 110054003,
    "RewardCount": 1
  },
  {
    "ID": 999058,
    "SubGroupID": 9999,
    "RewardType": "Active",
    "RewardID": 110052004,
    "RewardCount": 1
  },
  {
    "ID": 999059,
    "SubGroupID": 9999,
    "RewardType": "Active",
    "RewardID": 110053004,
    "RewardCount": 1
  },
  {
    "ID": 999060,
    "SubGroupID": 9999,
    "RewardType": "Active",
    "RewardID": 110054004,
    "RewardCount": 1
  },
  {
    "ID": 999061,
    "SubGroupID": 9999,
    "RewardType": "Active",
    "RewardID": 110062001,
    "RewardCount": 1
  },
  {
    "ID": 999062,
    "SubGroupID": 9999,
    "RewardType": "Active",
    "RewardID": 110063001,
    "RewardCount": 1
  },
  {
    "ID": 999063,
    "SubGroupID": 9999,
    "RewardType": "Active",
    "RewardID": 110064001,
    "RewardCount": 1
  },
  {
    "ID": 999064,
    "SubGroupID": 9999,
    "RewardType": "Active",
    "RewardID": 110062002,
    "RewardCount": 1
  },
  {
    "ID": 999065,
    "SubGroupID": 9999,
    "RewardType": "Active",
    "RewardID": 110063002,
    "RewardCount": 1
  },
  {
    "ID": 999066,
    "SubGroupID": 9999,
    "RewardType": "Active",
    "RewardID": 110064002,
    "RewardCount": 1
  },
  {
    "ID": 999067,
    "SubGroupID": 9999,
    "RewardType": "Active",
    "RewardID": 110062003,
    "RewardCount": 1
  },
  {
    "ID": 999068,
    "SubGroupID": 9999,
    "RewardType": "Active",
    "RewardID": 110063003,
    "RewardCount": 1
  },
  {
    "ID": 999069,
    "SubGroupID": 9999,
    "RewardType": "Active",
    "RewardID": 110064003,
    "RewardCount": 1
  },
  {
    "ID": 999070,
    "SubGroupID": 9999,
    "RewardType": "Active",
    "RewardID": 110062004,
    "RewardCount": 1
  },
  {
    "ID": 999071,
    "SubGroupID": 9999,
    "RewardType": "Active",
    "RewardID": 110063004,
    "RewardCount": 1
  },
  {
    "ID": 999072,
    "SubGroupID": 9999,
    "RewardType": "Active",
    "RewardID": 110064004,
    "RewardCount": 1
  },
  {
    "ID": 999073,
    "SubGroupID": 9999,
    "RewardType": "Active",
    "RewardID": 110072001,
    "RewardCount": 1
  },
  {
    "ID": 999074,
    "SubGroupID": 9999,
    "RewardType": "Active",
    "RewardID": 110073001,
    "RewardCount": 1
  },
  {
    "ID": 999075,
    "SubGroupID": 9999,
    "RewardType": "Active",
    "RewardID": 110074001,
    "RewardCount": 1
  },
  {
    "ID": 999076,
    "SubGroupID": 9999,
    "RewardType": "Active",
    "RewardID": 110072002,
    "RewardCount": 1
  },
  {
    "ID": 999077,
    "SubGroupID": 9999,
    "RewardType": "Active",
    "RewardID": 110073002,
    "RewardCount": 1
  },
  {
    "ID": 999078,
    "SubGroupID": 9999,
    "RewardType": "Active",
    "RewardID": 110074002,
    "RewardCount": 1
  },
  {
    "ID": 999079,
    "SubGroupID": 9999,
    "RewardType": "Active",
    "RewardID": 110072003,
    "RewardCount": 1
  },
  {
    "ID": 999080,
    "SubGroupID": 9999,
    "RewardType": "Active",
    "RewardID": 110073003,
    "RewardCount": 1
  },
  {
    "ID": 999081,
    "SubGroupID": 9999,
    "RewardType": "Active",
    "RewardID": 110074003,
    "RewardCount": 1
  },
  {
    "ID": 999082,
    "SubGroupID": 9999,
    "RewardType": "Active",
    "RewardID": 110072004,
    "RewardCount": 1
  },
  {
    "ID": 999083,
    "SubGroupID": 9999,
    "RewardType": "Active",
    "RewardID": 110073004,
    "RewardCount": 1
  },
  {
    "ID": 999084,
    "SubGroupID": 9999,
    "RewardType": "Active",
    "RewardID": 110074004,
    "RewardCount": 1
  },
  {
    "ID": 999085,
    "SubGroupID": 9999,
    "RewardType": "Active",
    "RewardID": 110082001,
    "RewardCount": 1
  },
  {
    "ID": 999086,
    "SubGroupID": 9999,
    "RewardType": "Active",
    "RewardID": 110083001,
    "RewardCount": 1
  },
  {
    "ID": 999087,
    "SubGroupID": 9999,
    "RewardType": "Active",
    "RewardID": 110084001,
    "RewardCount": 1
  },
  {
    "ID": 999088,
    "SubGroupID": 9999,
    "RewardType": "Active",
    "RewardID": 110082002,
    "RewardCount": 1
  },
  {
    "ID": 999089,
    "SubGroupID": 9999,
    "RewardType": "Active",
    "RewardID": 110083002,
    "RewardCount": 1
  },
  {
    "ID": 999090,
    "SubGroupID": 9999,
    "RewardType": "Active",
    "RewardID": 110084002,
    "RewardCount": 1
  },
  {
    "ID": 999091,
    "SubGroupID": 9999,
    "RewardType": "Active",
    "RewardID": 110082003,
    "RewardCount": 1
  },
  {
    "ID": 999092,
    "SubGroupID": 9999,
    "RewardType": "Active",
    "RewardID": 110083003,
    "RewardCount": 1
  },
  {
    "ID": 999093,
    "SubGroupID": 9999,
    "RewardType": "Active",
    "RewardID": 110084003,
    "RewardCount": 1
  },
  {
    "ID": 999094,
    "SubGroupID": 9999,
    "RewardType": "Active",
    "RewardID": 110082004,
    "RewardCount": 1
  },
  {
    "ID": 999095,
    "SubGroupID": 9999,
    "RewardType": "Active",
    "RewardID": 110083004,
    "RewardCount": 1
  },
  {
    "ID": 999096,
    "SubGroupID": 9999,
    "RewardType": "Active",
    "RewardID": 110084004,
    "RewardCount": 1
  },
  {
    "ID": 999097,
    "SubGroupID": 9999,
    "RewardType": "Active",
    "RewardID": 110092001,
    "RewardCount": 1
  },
  {
    "ID": 999098,
    "SubGroupID": 9999,
    "RewardType": "Active",
    "RewardID": 110093001,
    "RewardCount": 1
  },
  {
    "ID": 999099,
    "SubGroupID": 9999,
    "RewardType": "Active",
    "RewardID": 110094001,
    "RewardCount": 1
  },
  {
    "ID": 999100,
    "SubGroupID": 9999,
    "RewardType": "Active",
    "RewardID": 110092002,
    "RewardCount": 1
  },
  {
    "ID": 999101,
    "SubGroupID": 9999,
    "RewardType": "Active",
    "RewardID": 110093002,
    "RewardCount": 1
  },
  {
    "ID": 999102,
    "SubGroupID": 9999,
    "RewardType": "Active",
    "RewardID": 110094002,
    "RewardCount": 1
  },
  {
    "ID": 999103,
    "SubGroupID": 9999,
    "RewardType": "Active",
    "RewardID": 110092003,
    "RewardCount": 1
  },
  {
    "ID": 999104,
    "SubGroupID": 9999,
    "RewardType": "Active",
    "RewardID": 110093003,
    "RewardCount": 1
  },
  {
    "ID": 999105,
    "SubGroupID": 9999,
    "RewardType": "Active",
    "RewardID": 110094003,
    "RewardCount": 1
  },
  {
    "ID": 999106,
    "SubGroupID": 9999,
    "RewardType": "Active",
    "RewardID": 110092004,
    "RewardCount": 1
  },
  {
    "ID": 999107,
    "SubGroupID": 9999,
    "RewardType": "Active",
    "RewardID": 110093004,
    "RewardCount": 1
  },
  {
    "ID": 999108,
    "SubGroupID": 9999,
    "RewardType": "Active",
    "RewardID": 110094004,
    "RewardCount": 1
  },
  {
    "ID": 999109,
    "SubGroupID": 9999,
    "RewardType": "Active",
    "RewardID": 110102001,
    "RewardCount": 1
  },
  {
    "ID": 999110,
    "SubGroupID": 9999,
    "RewardType": "Active",
    "RewardID": 110103001,
    "RewardCount": 1
  },
  {
    "ID": 999111,
    "SubGroupID": 9999,
    "RewardType": "Active",
    "RewardID": 110104001,
    "RewardCount": 1
  },
  {
    "ID": 999112,
    "SubGroupID": 9999,
    "RewardType": "Active",
    "RewardID": 110102002,
    "RewardCount": 1
  },
  {
    "ID": 999113,
    "SubGroupID": 9999,
    "RewardType": "Active",
    "RewardID": 110103002,
    "RewardCount": 1
  },
  {
    "ID": 999114,
    "SubGroupID": 9999,
    "RewardType": "Active",
    "RewardID": 110104002,
    "RewardCount": 1
  },
  {
    "ID": 999115,
    "SubGroupID": 9999,
    "RewardType": "Active",
    "RewardID": 110102003,
    "RewardCount": 1
  },
  {
    "ID": 999116,
    "SubGroupID": 9999,
    "RewardType": "Active",
    "RewardID": 110103003,
    "RewardCount": 1
  },
  {
    "ID": 999117,
    "SubGroupID": 9999,
    "RewardType": "Active",
    "RewardID": 110104003,
    "RewardCount": 1
  },
  {
    "ID": 999118,
    "SubGroupID": 9999,
    "RewardType": "Active",
    "RewardID": 110102004,
    "RewardCount": 1
  },
  {
    "ID": 999119,
    "SubGroupID": 9999,
    "RewardType": "Active",
    "RewardID": 110103004,
    "RewardCount": 1
  },
  {
    "ID": 999120,
    "SubGroupID": 9999,
    "RewardType": "Active",
    "RewardID": 110104004,
    "RewardCount": 1
  },
  {
    "ID": 999121,
    "SubGroupID": 9999,
    "RewardType": "Active",
    "RewardID": 110112001,
    "RewardCount": 1
  },
  {
    "ID": 999122,
    "SubGroupID": 9999,
    "RewardType": "Active",
    "RewardID": 110113001,
    "RewardCount": 1
  },
  {
    "ID": 999123,
    "SubGroupID": 9999,
    "RewardType": "Active",
    "RewardID": 110114001,
    "RewardCount": 1
  },
  {
    "ID": 999124,
    "SubGroupID": 9999,
    "RewardType": "Active",
    "RewardID": 110112002,
    "RewardCount": 1
  },
  {
    "ID": 999125,
    "SubGroupID": 9999,
    "RewardType": "Active",
    "RewardID": 110113002,
    "RewardCount": 1
  },
  {
    "ID": 999126,
    "SubGroupID": 9999,
    "RewardType": "Active",
    "RewardID": 110114002,
    "RewardCount": 1
  },
  {
    "ID": 999127,
    "SubGroupID": 9999,
    "RewardType": "Active",
    "RewardID": 110112003,
    "RewardCount": 1
  },
  {
    "ID": 999128,
    "SubGroupID": 9999,
    "RewardType": "Active",
    "RewardID": 110113003,
    "RewardCount": 1
  },
  {
    "ID": 999129,
    "SubGroupID": 9999,
    "RewardType": "Active",
    "RewardID": 110114003,
    "RewardCount": 1
  },
  {
    "ID": 999130,
    "SubGroupID": 9999,
    "RewardType": "Active",
    "RewardID": 110112004,
    "RewardCount": 1
  },
  {
    "ID": 999131,
    "SubGroupID": 9999,
    "RewardType": "Active",
    "RewardID": 110113004,
    "RewardCount": 1
  },
  {
    "ID": 999132,
    "SubGroupID": 9999,
    "RewardType": "Active",
    "RewardID": 110114004,
    "RewardCount": 1
  },
  {
    "ID": 999133,
    "SubGroupID": 9999,
    "RewardType": "Active",
    "RewardID": 110122001,
    "RewardCount": 1
  },
  {
    "ID": 999134,
    "SubGroupID": 9999,
    "RewardType": "Active",
    "RewardID": 110123001,
    "RewardCount": 1
  },
  {
    "ID": 999135,
    "SubGroupID": 9999,
    "RewardType": "Active",
    "RewardID": 110124001,
    "RewardCount": 1
  },
  {
    "ID": 999136,
    "SubGroupID": 9999,
    "RewardType": "Active",
    "RewardID": 110122002,
    "RewardCount": 1
  },
  {
    "ID": 999137,
    "SubGroupID": 9999,
    "RewardType": "Active",
    "RewardID": 110123002,
    "RewardCount": 1
  },
  {
    "ID": 999138,
    "SubGroupID": 9999,
    "RewardType": "Active",
    "RewardID": 110124002,
    "RewardCount": 1
  },
  {
    "ID": 999139,
    "SubGroupID": 9999,
    "RewardType": "Active",
    "RewardID": 110122003,
    "RewardCount": 1
  },
  {
    "ID": 999140,
    "SubGroupID": 9999,
    "RewardType": "Active",
    "RewardID": 110123003,
    "RewardCount": 1
  },
  {
    "ID": 999141,
    "SubGroupID": 9999,
    "RewardType": "Active",
    "RewardID": 110124003,
    "RewardCount": 1
  },
  {
    "ID": 999142,
    "SubGroupID": 9999,
    "RewardType": "Active",
    "RewardID": 110122004,
    "RewardCount": 1
  },
  {
    "ID": 999143,
    "SubGroupID": 9999,
    "RewardType": "Active",
    "RewardID": 110123004,
    "RewardCount": 1
  },
  {
    "ID": 999144,
    "SubGroupID": 9999,
    "RewardType": "Active",
    "RewardID": 110124004,
    "RewardCount": 1
  },
  {
    "ID": 999145,
    "SubGroupID": 9999,
    "RewardType": "Active",
    "RewardID": 110132001,
    "RewardCount": 1
  },
  {
    "ID": 999146,
    "SubGroupID": 9999,
    "RewardType": "Active",
    "RewardID": 110133001,
    "RewardCount": 1
  },
  {
    "ID": 999147,
    "SubGroupID": 9999,
    "RewardType": "Active",
    "RewardID": 110134001,
    "RewardCount": 1
  },
  {
    "ID": 999148,
    "SubGroupID": 9999,
    "RewardType": "Active",
    "RewardID": 110132002,
    "RewardCount": 1
  },
  {
    "ID": 999149,
    "SubGroupID": 9999,
    "RewardType": "Active",
    "RewardID": 110133002,
    "RewardCount": 1
  },
  {
    "ID": 999150,
    "SubGroupID": 9999,
    "RewardType": "Active",
    "RewardID": 110134002,
    "RewardCount": 1
  },
  {
    "ID": 999151,
    "SubGroupID": 9999,
    "RewardType": "Active",
    "RewardID": 110132003,
    "RewardCount": 1
  },
  {
    "ID": 999152,
    "SubGroupID": 9999,
    "RewardType": "Active",
    "RewardID": 110133003,
    "RewardCount": 1
  },
  {
    "ID": 999153,
    "SubGroupID": 9999,
    "RewardType": "Active",
    "RewardID": 110134003,
    "RewardCount": 1
  },
  {
    "ID": 999154,
    "SubGroupID": 9999,
    "RewardType": "Active",
    "RewardID": 110132004,
    "RewardCount": 1
  },
  {
    "ID": 999155,
    "SubGroupID": 9999,
    "RewardType": "Active",
    "RewardID": 110133004,
    "RewardCount": 1
  },
  {
    "ID": 999156,
    "SubGroupID": 9999,
    "RewardType": "Active",
    "RewardID": 110134004,
    "RewardCount": 1
  },
  {
    "ID": 10018,
    "SubGroupID": 210004,
    "RewardType": "Material",
    "RewardID": 10050001,
    "RewardCount": 50
  },
  {
    "ID": 10019,
    "SubGroupID": 210004,
    "RewardType": "GateEnterPoint",
    "RewardID": 1000009,
    "RewardCount": 3
  },
  {
    "ID": 10020,
    "SubGroupID": 210004,
    "RewardType": "AdventEnterPoint",
    "RewardID": 1000015,
    "RewardCount": 2
  },
  {
    "ID": 10021,
    "SubGroupID": 210004,
    "RewardType": "IndunEnterPoint",
    "RewardID": 1000010,
    "RewardCount": 2
  },
  {
    "ID": 10022,
    "SubGroupID": 210004,
    "RewardType": "Material",
    "RewardID": 10090001,
    "RewardCount": 20
  },
  {
    "ID": 10023,
    "SubGroupID": 210004,
    "RewardType": "Gold",
    "RewardID": 1000003,
    "RewardCount": 100000
  },
  {
    "ID": 10024,
    "SubGroupID": 210005,
    "RewardType": "Material",
    "RewardID": 10050002,
    "RewardCount": 30
  },
  {
    "ID": 10025,
    "SubGroupID": 210005,
    "RewardType": "GateEnterPoint",
    "RewardID": 1000009,
    "RewardCount": 6
  },
  {
    "ID": 10026,
    "SubGroupID": 210005,
    "RewardType": "AdventEnterPoint",
    "RewardID": 1000015,
    "RewardCount": 4
  },
  {
    "ID": 10027,
    "SubGroupID": 210005,
    "RewardType": "IndunEnterPoint",
    "RewardID": 1000010,
    "RewardCount": 4
  },
  {
    "ID": 10028,
    "SubGroupID": 210005,
    "RewardType": "Material",
    "RewardID": 10090001,
    "RewardCount": 50
  },
  {
    "ID": 10029,
    "SubGroupID": 210005,
    "RewardType": "Gold",
    "RewardID": 1000003,
    "RewardCount": 300000
  },
  {
    "ID": 10078,
    "SubGroupID": 1091010,
    "RewardType": "Active",
    "RewardID": 110013001,
    "RewardCount": 1
  },
  {
    "ID": 10079,
    "SubGroupID": 1091010,
    "RewardType": "Active",
    "RewardID": 110013002,
    "RewardCount": 1
  },
  {
    "ID": 10080,
    "SubGroupID": 1091010,
    "RewardType": "Active",
    "RewardID": 110013003,
    "RewardCount": 1
  },
  {
    "ID": 10081,
    "SubGroupID": 1091010,
    "RewardType": "Active",
    "RewardID": 110013004,
    "RewardCount": 1
  },
  {
    "ID": 10082,
    "SubGroupID": 1091010,
    "RewardType": "Active",
    "RewardID": 110023001,
    "RewardCount": 1
  },
  {
    "ID": 10083,
    "SubGroupID": 1091010,
    "RewardType": "Active",
    "RewardID": 110023002,
    "RewardCount": 1
  },
  {
    "ID": 10084,
    "SubGroupID": 1091010,
    "RewardType": "Active",
    "RewardID": 110023003,
    "RewardCount": 1
  },
  {
    "ID": 10085,
    "SubGroupID": 1091010,
    "RewardType": "Active",
    "RewardID": 110023004,
    "RewardCount": 1
  },
  {
    "ID": 10086,
    "SubGroupID": 1091010,
    "RewardType": "Active",
    "RewardID": 110033001,
    "RewardCount": 1
  },
  {
    "ID": 10087,
    "SubGroupID": 1091010,
    "RewardType": "Active",
    "RewardID": 110033002,
    "RewardCount": 1
  },
  {
    "ID": 10088,
    "SubGroupID": 1091010,
    "RewardType": "Active",
    "RewardID": 110033003,
    "RewardCount": 1
  },
  {
    "ID": 10089,
    "SubGroupID": 1091010,
    "RewardType": "Active",
    "RewardID": 110033004,
    "RewardCount": 1
  },
  {
    "ID": 10090,
    "SubGroupID": 1091010,
    "RewardType": "Active",
    "RewardID": 110043001,
    "RewardCount": 1
  },
  {
    "ID": 10091,
    "SubGroupID": 1091010,
    "RewardType": "Active",
    "RewardID": 110043002,
    "RewardCount": 1
  },
  {
    "ID": 10092,
    "SubGroupID": 1091010,
    "RewardType": "Active",
    "RewardID": 110043003,
    "RewardCount": 1
  },
  {
    "ID": 10093,
    "SubGroupID": 1091010,
    "RewardType": "Active",
    "RewardID": 110043004,
    "RewardCount": 1
  },
  {
    "ID": 10094,
    "SubGroupID": 1091010,
    "RewardType": "Active",
    "RewardID": 110053001,
    "RewardCount": 1
  },
  {
    "ID": 10095,
    "SubGroupID": 1091010,
    "RewardType": "Active",
    "RewardID": 110053002,
    "RewardCount": 1
  },
  {
    "ID": 10096,
    "SubGroupID": 1091010,
    "RewardType": "Active",
    "RewardID": 110053003,
    "RewardCount": 1
  },
  {
    "ID": 10097,
    "SubGroupID": 1091010,
    "RewardType": "Active",
    "RewardID": 110053004,
    "RewardCount": 1
  },
  {
    "ID": 10098,
    "SubGroupID": 1091010,
    "RewardType": "Active",
    "RewardID": 110063001,
    "RewardCount": 1
  },
  {
    "ID": 10099,
    "SubGroupID": 1091010,
    "RewardType": "Active",
    "RewardID": 110063002,
    "RewardCount": 1
  },
  {
    "ID": 10100,
    "SubGroupID": 1091010,
    "RewardType": "Active",
    "RewardID": 110063003,
    "RewardCount": 1
  },
  {
    "ID": 10101,
    "SubGroupID": 1091010,
    "RewardType": "Active",
    "RewardID": 110063004,
    "RewardCount": 1
  },
  {
    "ID": 10102,
    "SubGroupID": 1091010,
    "RewardType": "Active",
    "RewardID": 110083001,
    "RewardCount": 1
  },
  {
    "ID": 10103,
    "SubGroupID": 1091010,
    "RewardType": "Active",
    "RewardID": 110083002,
    "RewardCount": 1
  },
  {
    "ID": 10104,
    "SubGroupID": 1091010,
    "RewardType": "Active",
    "RewardID": 110083003,
    "RewardCount": 1
  },
  {
    "ID": 10105,
    "SubGroupID": 1091010,
    "RewardType": "Active",
    "RewardID": 110083004,
    "RewardCount": 1
  },
  {
    "ID": 10106,
    "SubGroupID": 1091010,
    "RewardType": "Active",
    "RewardID": 110093001,
    "RewardCount": 1
  },
  {
    "ID": 10107,
    "SubGroupID": 1091010,
    "RewardType": "Active",
    "RewardID": 110093002,
    "RewardCount": 1
  },
  {
    "ID": 10108,
    "SubGroupID": 1091010,
    "RewardType": "Active",
    "RewardID": 110093003,
    "RewardCount": 1
  },
  {
    "ID": 10109,
    "SubGroupID": 1091010,
    "RewardType": "Active",
    "RewardID": 110093004,
    "RewardCount": 1
  },
  {
    "ID": 10110,
    "SubGroupID": 1091010,
    "RewardType": "Active",
    "RewardID": 110103001,
    "RewardCount": 1
  },
  {
    "ID": 10111,
    "SubGroupID": 1091010,
    "RewardType": "Active",
    "RewardID": 110103002,
    "RewardCount": 1
  },
  {
    "ID": 10112,
    "SubGroupID": 1091010,
    "RewardType": "Active",
    "RewardID": 110103003,
    "RewardCount": 1
  },
  {
    "ID": 10113,
    "SubGroupID": 1091010,
    "RewardType": "Active",
    "RewardID": 110103004,
    "RewardCount": 1
  },
  {
    "ID": 10114,
    "SubGroupID": 1091010,
    "RewardType": "Active",
    "RewardID": 110113001,
    "RewardCount": 1
  },
  {
    "ID": 10115,
    "SubGroupID": 1091010,
    "RewardType": "Active",
    "RewardID": 110113002,
    "RewardCount": 1
  },
  {
    "ID": 10116,
    "SubGroupID": 1091010,
    "RewardType": "Active",
    "RewardID": 110113003,
    "RewardCount": 1
  },
  {
    "ID": 10117,
    "SubGroupID": 1091010,
    "RewardType": "Active",
    "RewardID": 110113004,
    "RewardCount": 1
  },
  {
    "ID": 10118,
    "SubGroupID": 1091010,
    "RewardType": "Active",
    "RewardID": 110073001,
    "RewardCount": 1
  },
  {
    "ID": 10119,
    "SubGroupID": 1091010,
    "RewardType": "Active",
    "RewardID": 110073002,
    "RewardCount": 1
  },
  {
    "ID": 10120,
    "SubGroupID": 1091010,
    "RewardType": "Active",
    "RewardID": 110073003,
    "RewardCount": 1
  },
  {
    "ID": 10121,
    "SubGroupID": 1091010,
    "RewardType": "Active",
    "RewardID": 110073004,
    "RewardCount": 1
  },
  {
    "ID": 10122,
    "SubGroupID": 1091011,
    "RewardType": "Emblem",
    "RewardID": 120013000,
    "RewardCount": 1
  },
  {
    "ID": 10123,
    "SubGroupID": 1091011,
    "RewardType": "Emblem",
    "RewardID": 120023000,
    "RewardCount": 1
  },
  {
    "ID": 10124,
    "SubGroupID": 1091011,
    "RewardType": "Emblem",
    "RewardID": 120033000,
    "RewardCount": 1
  },
  {
    "ID": 10125,
    "SubGroupID": 1091011,
    "RewardType": "Emblem",
    "RewardID": 120043000,
    "RewardCount": 1
  },
  {
    "ID": 10126,
    "SubGroupID": 1091011,
    "RewardType": "Emblem",
    "RewardID": 120053000,
    "RewardCount": 1
  },
  {
    "ID": 10127,
    "SubGroupID": 1091011,
    "RewardType": "Emblem",
    "RewardID": 120063000,
    "RewardCount": 1
  },
  {
    "ID": 10128,
    "SubGroupID": 1091011,
    "RewardType": "Emblem",
    "RewardID": 120073000,
    "RewardCount": 1
  },
  {
    "ID": 10129,
    "SubGroupID": 1091011,
    "RewardType": "Emblem",
    "RewardID": 120083000,
    "RewardCount": 1
  },
  {
    "ID": 10130,
    "SubGroupID": 1091011,
    "RewardType": "Emblem",
    "RewardID": 120093000,
    "RewardCount": 1
  },
  {
    "ID": 10131,
    "SubGroupID": 1091011,
    "RewardType": "Emblem",
    "RewardID": 120103000,
    "RewardCount": 1
  },
  {
    "ID": 10133,
    "SubGroupID": 1091011,
    "RewardType": "Emblem",
    "RewardID": 120123000,
    "RewardCount": 1
  },
  {
    "ID": 10134,
    "SubGroupID": 1091011,
    "RewardType": "Emblem",
    "RewardID": 120133000,
    "RewardCount": 1
  },
  {
    "ID": 10135,
    "SubGroupID": 1091011,
    "RewardType": "Emblem",
    "RewardID": 120143000,
    "RewardCount": 1
  },
  {
    "ID": 10136,
    "SubGroupID": 1091011,
    "RewardType": "Emblem",
    "RewardID": 120153000,
    "RewardCount": 1
  },
  {
    "ID": 10137,
    "SubGroupID": 1091011,
    "RewardType": "Emblem",
    "RewardID": 120163000,
    "RewardCount": 1
  },
  {
    "ID": 10138,
    "SubGroupID": 1091011,
    "RewardType": "Emblem",
    "RewardID": 120173000,
    "RewardCount": 1
  },
  {
    "ID": 10139,
    "SubGroupID": 1091011,
    "RewardType": "Emblem",
    "RewardID": 120183000,
    "RewardCount": 1
  },
  {
    "ID": 10140,
    "SubGroupID": 1091011,
    "RewardType": "Emblem",
    "RewardID": 120193000,
    "RewardCount": 1
  },
  {
    "ID": 10141,
    "SubGroupID": 1091011,
    "RewardType": "Emblem",
    "RewardID": 120203000,
    "RewardCount": 1
  },
  {
    "ID": 10142,
    "SubGroupID": 1091011,
    "RewardType": "Emblem",
    "RewardID": 120213000,
    "RewardCount": 1
  },
  {
    "ID": 10143,
    "SubGroupID": 1091011,
    "RewardType": "Emblem",
    "RewardID": 120223000,
    "RewardCount": 1
  },
  {
    "ID": 10144,
    "SubGroupID": 1091011,
    "RewardType": "Emblem",
    "RewardID": 120233000,
    "RewardCount": 1
  },
  {
    "ID": 10145,
    "SubGroupID": 1091011,
    "RewardType": "Emblem",
    "RewardID": 120243000,
    "RewardCount": 1
  },
  {
    "ID": 10146,
    "SubGroupID": 1091011,
    "RewardType": "Emblem",
    "RewardID": 120253000,
    "RewardCount": 1
  },
  {
    "ID": 10147,
    "SubGroupID": 20200022,
    "RewardType": "Relic",
    "RewardID": 301010040,
    "RewardCount": 1
  },
  {
    "ID": 10148,
    "SubGroupID": 20200022,
    "RewardType": "Relic",
    "RewardID": 301010041,
    "RewardCount": 1
  },
  {
    "ID": 10149,
    "SubGroupID": 20200022,
    "RewardType": "Relic",
    "RewardID": 301010042,
    "RewardCount": 1
  },
  {
    "ID": 10150,
    "SubGroupID": 10150003,
    "RewardType": "Material",
    "RewardID": 10150001,
    "RewardCount": 1
  },
  {
    "ID": 10151,
    "SubGroupID": 10150003,
    "RewardType": "Material",
    "RewardID": 10150002,
    "RewardCount": 1
  },
  {
    "ID": 10152,
    "SubGroupID": 20200023,
    "RewardType": "Relic",
    "RewardID": 302030020,
    "RewardCount": 1
  },
  {
    "ID": 10153,
    "SubGroupID": 20200023,
    "RewardType": "Relic",
    "RewardID": 302030019,
    "RewardCount": 1
  },
  {
    "ID": 10154,
    "SubGroupID": 20200024,
    "RewardType": "GS",
    "RewardID": 200020005,
    "RewardCount": 1
  },
  {
    "ID": 10155,
    "SubGroupID": 20200024,
    "RewardType": "GS",
    "RewardID": 200030005,
    "RewardCount": 1
  },
  {
    "ID": 10156,
    "SubGroupID": 20200024,
    "RewardType": "GS",
    "RewardID": 200030006,
    "RewardCount": 1
  },
  {
    "ID": 10157,
    "SubGroupID": 20200024,
    "RewardType": "GS",
    "RewardID": 200030013,
    "RewardCount": 1
  },
  {
    "ID": 10159,
    "SubGroupID": 10150006,
    "RewardType": "Material",
    "RewardID": 10150004,
    "RewardCount": 1
  },
  {
    "ID": 10160,
    "SubGroupID": 10150006,
    "RewardType": "Material",
    "RewardID": 10150005,
    "RewardCount": 1
  },
  {
    "ID": 10161,
    "SubGroupID": 20200025,
    "RewardType": "Relic",
    "RewardID": 302030021,
    "RewardCount": 1
  },
  {
    "ID": 10162,
    "SubGroupID": 20200025,
    "RewardType": "Relic",
    "RewardID": 302030022,
    "RewardCount": 1
  },
  {
    "ID": 10163,
    "SubGroupID": 20200102,
    "RewardType": "Active",
    "RewardID": 110013001,
    "RewardCount": 1
  },
  {
    "ID": 10164,
    "SubGroupID": 20200102,
    "RewardType": "Active",
    "RewardID": 110013002,
    "RewardCount": 1
  },
  {
    "ID": 10165,
    "SubGroupID": 20200102,
    "RewardType": "Active",
    "RewardID": 110013003,
    "RewardCount": 1
  },
  {
    "ID": 10166,
    "SubGroupID": 20200102,
    "RewardType": "Active",
    "RewardID": 110013004,
    "RewardCount": 1
  },
  {
    "ID": 10167,
    "SubGroupID": 20200102,
    "RewardType": "Active",
    "RewardID": 110023001,
    "RewardCount": 1
  },
  {
    "ID": 10168,
    "SubGroupID": 20200102,
    "RewardType": "Active",
    "RewardID": 110023002,
    "RewardCount": 1
  },
  {
    "ID": 10169,
    "SubGroupID": 20200102,
    "RewardType": "Active",
    "RewardID": 110023003,
    "RewardCount": 1
  },
  {
    "ID": 10170,
    "SubGroupID": 20200102,
    "RewardType": "Active",
    "RewardID": 110023004,
    "RewardCount": 1
  },
  {
    "ID": 10171,
    "SubGroupID": 20200102,
    "RewardType": "Active",
    "RewardID": 110033001,
    "RewardCount": 1
  },
  {
    "ID": 10172,
    "SubGroupID": 20200102,
    "RewardType": "Active",
    "RewardID": 110033002,
    "RewardCount": 1
  },
  {
    "ID": 10173,
    "SubGroupID": 20200102,
    "RewardType": "Active",
    "RewardID": 110033003,
    "RewardCount": 1
  },
  {
    "ID": 10174,
    "SubGroupID": 20200102,
    "RewardType": "Active",
    "RewardID": 110033004,
    "RewardCount": 1
  },
  {
    "ID": 10175,
    "SubGroupID": 20200102,
    "RewardType": "Active",
    "RewardID": 110043001,
    "RewardCount": 1
  },
  {
    "ID": 10176,
    "SubGroupID": 20200102,
    "RewardType": "Active",
    "RewardID": 110043002,
    "RewardCount": 1
  },
  {
    "ID": 10177,
    "SubGroupID": 20200102,
    "RewardType": "Active",
    "RewardID": 110043003,
    "RewardCount": 1
  },
  {
    "ID": 10178,
    "SubGroupID": 20200102,
    "RewardType": "Active",
    "RewardID": 110043004,
    "RewardCount": 1
  },
  {
    "ID": 10179,
    "SubGroupID": 20200102,
    "RewardType": "Active",
    "RewardID": 110053001,
    "RewardCount": 1
  },
  {
    "ID": 10180,
    "SubGroupID": 20200102,
    "RewardType": "Active",
    "RewardID": 110053002,
    "RewardCount": 1
  },
  {
    "ID": 10181,
    "SubGroupID": 20200102,
    "RewardType": "Active",
    "RewardID": 110053003,
    "RewardCount": 1
  },
  {
    "ID": 10182,
    "SubGroupID": 20200102,
    "RewardType": "Active",
    "RewardID": 110053004,
    "RewardCount": 1
  },
  {
    "ID": 10183,
    "SubGroupID": 20200102,
    "RewardType": "Active",
    "RewardID": 110063001,
    "RewardCount": 1
  },
  {
    "ID": 10184,
    "SubGroupID": 20200102,
    "RewardType": "Active",
    "RewardID": 110063002,
    "RewardCount": 1
  },
  {
    "ID": 10185,
    "SubGroupID": 20200102,
    "RewardType": "Active",
    "RewardID": 110063003,
    "RewardCount": 1
  },
  {
    "ID": 10186,
    "SubGroupID": 20200102,
    "RewardType": "Active",
    "RewardID": 110063004,
    "RewardCount": 1
  },
  {
    "ID": 10187,
    "SubGroupID": 20200102,
    "RewardType": "Active",
    "RewardID": 110123001,
    "RewardCount": 1
  },
  {
    "ID": 10188,
    "SubGroupID": 20200102,
    "RewardType": "Active",
    "RewardID": 110123002,
    "RewardCount": 1
  },
  {
    "ID": 10189,
    "SubGroupID": 20200102,
    "RewardType": "Active",
    "RewardID": 110123003,
    "RewardCount": 1
  },
  {
    "ID": 10190,
    "SubGroupID": 20200102,
    "RewardType": "Active",
    "RewardID": 110123004,
    "RewardCount": 1
  },
  {
    "ID": 10191,
    "SubGroupID": 20200102,
    "RewardType": "Active",
    "RewardID": 110083001,
    "RewardCount": 1
  },
  {
    "ID": 10192,
    "SubGroupID": 20200102,
    "RewardType": "Active",
    "RewardID": 110083002,
    "RewardCount": 1
  },
  {
    "ID": 10193,
    "SubGroupID": 20200102,
    "RewardType": "Active",
    "RewardID": 110083003,
    "RewardCount": 1
  },
  {
    "ID": 10194,
    "SubGroupID": 20200102,
    "RewardType": "Active",
    "RewardID": 110083004,
    "RewardCount": 1
  },
  {
    "ID": 10195,
    "SubGroupID": 20200102,
    "RewardType": "Active",
    "RewardID": 110093001,
    "RewardCount": 1
  },
  {
    "ID": 10196,
    "SubGroupID": 20200102,
    "RewardType": "Active",
    "RewardID": 110093002,
    "RewardCount": 1
  },
  {
    "ID": 10197,
    "SubGroupID": 20200102,
    "RewardType": "Active",
    "RewardID": 110093003,
    "RewardCount": 1
  },
  {
    "ID": 10198,
    "SubGroupID": 20200102,
    "RewardType": "Active",
    "RewardID": 110093004,
    "RewardCount": 1
  },
  {
    "ID": 10199,
    "SubGroupID": 20200102,
    "RewardType": "Active",
    "RewardID": 110103001,
    "RewardCount": 1
  },
  {
    "ID": 10200,
    "SubGroupID": 20200102,
    "RewardType": "Active",
    "RewardID": 110103002,
    "RewardCount": 1
  },
  {
    "ID": 10201,
    "SubGroupID": 20200102,
    "RewardType": "Active",
    "RewardID": 110103003,
    "RewardCount": 1
  },
  {
    "ID": 10202,
    "SubGroupID": 20200102,
    "RewardType": "Active",
    "RewardID": 110103004,
    "RewardCount": 1
  },
  {
    "ID": 10203,
    "SubGroupID": 20200102,
    "RewardType": "Active",
    "RewardID": 110113001,
    "RewardCount": 1
  },
  {
    "ID": 10204,
    "SubGroupID": 20200102,
    "RewardType": "Active",
    "RewardID": 110113002,
    "RewardCount": 1
  },
  {
    "ID": 10205,
    "SubGroupID": 20200102,
    "RewardType": "Active",
    "RewardID": 110113003,
    "RewardCount": 1
  },
  {
    "ID": 10206,
    "SubGroupID": 20200102,
    "RewardType": "Active",
    "RewardID": 110113004,
    "RewardCount": 1
  },
  {
    "ID": 10207,
    "SubGroupID": 20200102,
    "RewardType": "Active",
    "RewardID": 110073001,
    "RewardCount": 1
  },
  {
    "ID": 10208,
    "SubGroupID": 20200102,
    "RewardType": "Active",
    "RewardID": 110073002,
    "RewardCount": 1
  },
  {
    "ID": 10209,
    "SubGroupID": 20200102,
    "RewardType": "Active",
    "RewardID": 110073003,
    "RewardCount": 1
  },
  {
    "ID": 10210,
    "SubGroupID": 20200102,
    "RewardType": "Active",
    "RewardID": 110073004,
    "RewardCount": 1
  },
  {
    "ID": 10211,
    "SubGroupID": 20200103,
    "RewardType": "Emblem",
    "RewardID": 120013000,
    "RewardCount": 1
  },
  {
    "ID": 10212,
    "SubGroupID": 20200103,
    "RewardType": "Emblem",
    "RewardID": 120023000,
    "RewardCount": 1
  },
  {
    "ID": 10213,
    "SubGroupID": 20200103,
    "RewardType": "Emblem",
    "RewardID": 120033000,
    "RewardCount": 1
  },
  {
    "ID": 10214,
    "SubGroupID": 20200103,
    "RewardType": "Emblem",
    "RewardID": 120043000,
    "RewardCount": 1
  },
  {
    "ID": 10215,
    "SubGroupID": 20200103,
    "RewardType": "Emblem",
    "RewardID": 120053000,
    "RewardCount": 1
  },
  {
    "ID": 10216,
    "SubGroupID": 20200103,
    "RewardType": "Emblem",
    "RewardID": 120063000,
    "RewardCount": 1
  },
  {
    "ID": 10217,
    "SubGroupID": 20200103,
    "RewardType": "Emblem",
    "RewardID": 120073000,
    "RewardCount": 1
  },
  {
    "ID": 10218,
    "SubGroupID": 20200103,
    "RewardType": "Emblem",
    "RewardID": 120083000,
    "RewardCount": 1
  },
  {
    "ID": 10219,
    "SubGroupID": 20200103,
    "RewardType": "Emblem",
    "RewardID": 120093000,
    "RewardCount": 1
  },
  {
    "ID": 10220,
    "SubGroupID": 20200103,
    "RewardType": "Emblem",
    "RewardID": 120103000,
    "RewardCount": 1
  },
  {
    "ID": 10221,
    "SubGroupID": 20200103,
    "RewardType": "Emblem",
    "RewardID": 120123000,
    "RewardCount": 1
  },
  {
    "ID": 10222,
    "SubGroupID": 20200103,
    "RewardType": "Emblem",
    "RewardID": 120133000,
    "RewardCount": 1
  },
  {
    "ID": 10223,
    "SubGroupID": 20200103,
    "RewardType": "Emblem",
    "RewardID": 120143000,
    "RewardCount": 1
  },
  {
    "ID": 10224,
    "SubGroupID": 20200103,
    "RewardType": "Emblem",
    "RewardID": 120153000,
    "RewardCount": 1
  },
  {
    "ID": 10225,
    "SubGroupID": 20200103,
    "RewardType": "Emblem",
    "RewardID": 120163000,
    "RewardCount": 1
  },
  {
    "ID": 10226,
    "SubGroupID": 20200103,
    "RewardType": "Emblem",
    "RewardID": 120173000,
    "RewardCount": 1
  },
  {
    "ID": 10227,
    "SubGroupID": 20200103,
    "RewardType": "Emblem",
    "RewardID": 120183000,
    "RewardCount": 1
  },
  {
    "ID": 10228,
    "SubGroupID": 20200103,
    "RewardType": "Emblem",
    "RewardID": 120193000,
    "RewardCount": 1
  },
  {
    "ID": 10229,
    "SubGroupID": 20200103,
    "RewardType": "Emblem",
    "RewardID": 120203000,
    "RewardCount": 1
  },
  {
    "ID": 10230,
    "SubGroupID": 20200103,
    "RewardType": "Emblem",
    "RewardID": 120213000,
    "RewardCount": 1
  },
  {
    "ID": 10231,
    "SubGroupID": 20200103,
    "RewardType": "Emblem",
    "RewardID": 120223000,
    "RewardCount": 1
  },
  {
    "ID": 10232,
    "SubGroupID": 20200103,
    "RewardType": "Emblem",
    "RewardID": 120233000,
    "RewardCount": 1
  },
  {
    "ID": 10233,
    "SubGroupID": 20200103,
    "RewardType": "Emblem",
    "RewardID": 120243000,
    "RewardCount": 1
  },
  {
    "ID": 10234,
    "SubGroupID": 20200103,
    "RewardType": "Emblem",
    "RewardID": 120253000,
    "RewardCount": 1
  },
  {
    "ID": 10235,
    "SubGroupID": 20200103,
    "RewardType": "Emblem",
    "RewardID": 120263000,
    "RewardCount": 1
  },
  {
    "ID": 10236,
    "SubGroupID": 20200103,
    "RewardType": "Emblem",
    "RewardID": 120273000,
    "RewardCount": 1
  },
  {
    "ID": 10238,
    "SubGroupID": 20200104,
    "RewardType": "UseItem",
    "RewardID": 20700022,
    "RewardCount": 1
  },
  {
    "ID": 10239,
    "SubGroupID": 20200104,
    "RewardType": "UseItem",
    "RewardID": 20700023,
    "RewardCount": 1
  },
  {
    "ID": 10240,
    "SubGroupID": 20200104,
    "RewardType": "UseItem",
    "RewardID": 20700024,
    "RewardCount": 1
  },
  {
    "ID": 10241,
    "SubGroupID": 20200104,
    "RewardType": "UseItem",
    "RewardID": 20700025,
    "RewardCount": 1
  },
  {
    "ID": 10242,
    "SubGroupID": 20200104,
    "RewardType": "UseItem",
    "RewardID": 20700026,
    "RewardCount": 1
  },
  {
    "ID": 10243,
    "SubGroupID": 20200104,
    "RewardType": "UseItem",
    "RewardID": 20700027,
    "RewardCount": 1
  },
  {
    "ID": 10244,
    "SubGroupID": 20200104,
    "RewardType": "UseItem",
    "RewardID": 20700028,
    "RewardCount": 1
  },
  {
    "ID": 10245,
    "SubGroupID": 20200104,
    "RewardType": "UseItem",
    "RewardID": 20700029,
    "RewardCount": 1
  },
  {
    "ID": 10246,
    "SubGroupID": 20200104,
    "RewardType": "UseItem",
    "RewardID": 20700030,
    "RewardCount": 1
  },
  {
    "ID": 10247,
    "SubGroupID": 20200104,
    "RewardType": "UseItem",
    "RewardID": 20700031,
    "RewardCount": 1
  },
  {
    "ID": 10248,
    "SubGroupID": 20200104,
    "RewardType": "UseItem",
    "RewardID": 20700032,
    "RewardCount": 1
  },
  {
    "ID": 10249,
    "SubGroupID": 20200104,
    "RewardType": "UseItem",
    "RewardID": 20700033,
    "RewardCount": 1
  },
  {
    "ID": 10250,
    "SubGroupID": 10150008,
    "RewardType": "Material",
    "RewardID": 10150007,
    "RewardCount": 1
  },
  {
    "ID": 10251,
    "SubGroupID": 10150008,
    "RewardType": "Material",
    "RewardID": 10150004,
    "RewardCount": 1
  },
  {
    "ID": 10252,
    "SubGroupID": 10150008,
    "RewardType": "Material",
    "RewardID": 10150005,
    "RewardCount": 1
  }
]